CHANGES.TXT
LICENCE.TXT
README.TXT
setup.cfg
setup.py
tox.ini
doc/html/genindex.html
doc/html/index.html
doc/html/ivalutils.html
doc/html/objects.inv
doc/html/py-modindex.html
doc/html/search.html
doc/html/searchindex.js
doc/html/_sources/index.rst.txt
doc/html/_sources/ivalutils.rst.txt
doc/html/_sources/html/intro.rst.txt
doc/html/_static/ajax-loader.gif
doc/html/_static/basic.css
doc/html/_static/classic.css
doc/html/_static/comment-bright.png
doc/html/_static/comment-close.png
doc/html/_static/comment.png
doc/html/_static/copybutton.js
doc/html/_static/doctools.js
doc/html/_static/down-pressed.png
doc/html/_static/down.png
doc/html/_static/favicon.png
doc/html/_static/file.png
doc/html/_static/jquery-3.1.0.js
doc/html/_static/jquery.js
doc/html/_static/minus.png
doc/html/_static/plus.png
doc/html/_static/pydoctheme.css
doc/html/_static/pygments.css
doc/html/_static/right-red@2x.png
doc/html/_static/searchtools.js
doc/html/_static/sidebar.js
doc/html/_static/underscore-1.3.1.js
doc/html/_static/underscore.js
doc/html/_static/up-pressed.png
doc/html/_static/up.png
doc/html/_static/websupport.js
doc/html/html/intro.html
ivalutils/__init__.py
ivalutils/interval.py
ivalutils/interval_chain.py
ivalutils/interval_map.py
ivalutils.egg-info/PKG-INFO
ivalutils.egg-info/SOURCES.txt
ivalutils.egg-info/dependency_links.txt
ivalutils.egg-info/top_level.txt
ivalutils/tests/test_interval.py
ivalutils/tests/test_interval_chain.py
ivalutils/tests/test_interval_map.py